iPyCat-0.0.14.data/scripts/ipycat
utils/__init__.py
utils/nuage_mots.py
utils/stop_words.py
iPyCat-0.0.14.dist-info/LICENSE
iPyCat-0.0.14.dist-info/METADATA
iPyCat-0.0.14.dist-info/WHEEL
iPyCat-0.0.14.dist-info/top_level.txt
iPyCat-0.0.14.dist-info/RECORD
