Metadata-Version: 2.1
Name: iPyCat
Version: 0.0.14
Summary: Interface Python en ligne de Commande pour les Analyses de Textes.
Home-page: https://github.com/demangejeremy/iPyCAT
Author: Jérémy DEMANGE
Author-email: jeremy.demange.mail@gmail.com
License: UNKNOWN
Platform: UNKNOWN
Classifier: Programming Language :: Python :: 3
Classifier: License :: OSI Approved :: MIT License
Classifier: Operating System :: OS Independent
Requires-Dist: wordcloud
Requires-Dist: nltk
Requires-Dist: numpy
Requires-Dist: requests
Requires-Dist: click
